MANIFEST.in
README.rst
setup.py
py_thesaurus/__init__.py
py_thesaurus/base_class.py
py_thesaurus/custom_exceptions.py
py_thesaurus/main.py
py_thesaurus.egg-info/PKG-INFO
py_thesaurus.egg-info/SOURCES.txt
py_thesaurus.egg-info/dependency_links.txt
py_thesaurus.egg-info/entry_points.txt
py_thesaurus.egg-info/not-zip-safe
py_thesaurus.egg-info/requires.txt
py_thesaurus.egg-info/top_level.txt