Metadata-Version: 1.1
Name: py-thesaurus
Version: 1.0.4
Summary: To fetch the thesaurus of an input word
Home-page: https://bitbucket.org/redpills01/py_thesaurus.git
Author: red_pills
Author-email: redpillsworkspace@gmail.com
License: MIT
Keywords: nlp text-mining
Platform: UNKNOWN
Classifier: Development Status :: 5 - Production/Stable
Classifier: Intended Audience :: Developers
Classifier: Intended Audience :: Education
Classifier: Intended Audience :: Information Technology
Classifier: Intended Audience :: Manufacturing
Classifier: Intended Audience :: Other Audience
Classifier: Intended Audience :: Science/Research
Classifier: Programming Language :: Python :: 3.4
Classifier: Programming Language :: Python :: 3.5
Classifier: Programming Language :: Python :: 3.6
Classifier: Programming Language :: Python :: 3.7
Classifier: License :: OSI Approved :: MIT License
Classifier: Natural Language :: English
Classifier: Topic :: Text Processing :: Linguistic
